CHANGELOG.txt
LICENCE.txt
MANIFEST.in
README.txt
setup.py
whatsappapi/__init__.py
whatsappapi/chromedriver.exe
whatsappapi.egg-info/PKG-INFO
whatsappapi.egg-info/SOURCES.txt
whatsappapi.egg-info/dependency_links.txt
whatsappapi.egg-info/requires.txt
whatsappapi.egg-info/top_level.txt