Metadata-Version: 1.1
Name: whatsappapi
Version: 2.6.0
Summary: A Basic Beta Whatsapp API
Home-page: UNKNOWN
Author: Enzo Barizza Leal
Author-email: enzobarizza@gmail.com
License: MIT
Keywords: whatsapp
Platform: UNKNOWN
Classifier: Development Status :: 5 - Production/Stable
Classifier: Intended Audience :: Education
Classifier: Operating System :: Microsoft :: Windows :: Windows 10
Classifier: License :: OSI Approved :: MIT License
Classifier: Programming Language :: Python :: 3
